cloudwatch/__init__.py
cloudwatch/cloudwatch.py
cloudwatch-1.2.2.dist-info/LICENSE
cloudwatch-1.2.2.dist-info/METADATA
cloudwatch-1.2.2.dist-info/WHEEL
cloudwatch-1.2.2.dist-info/top_level.txt
cloudwatch-1.2.2.dist-info/RECORD
