Metadata-Version: 2.1
Name: cloudwatch
Version: 1.2.2
Summary: A small handler for AWS Cloudwatch
Author: Ernesto Monroy
Project-URL: Homepage, https://github.com/labrixdigital/cloudwatch
Project-URL: Bug Tracker, https://github.com/labrixdigital/cloudwatch/issues
Keywords: cloudwatch,aws,boto3,logging,logger
Classifier: Programming Language :: Python :: 3
Classifier: License :: OSI Approved :: MIT License
Classifier: Operating System :: OS Independent
Classifier: Intended Audience :: Developers
Classifier: Development Status :: 5 - Production/Stable
Classifier: Topic :: Utilities
Requires-Python: >=3.5
License-File: LICENSE
Requires-Dist: boto3
